ac_core/__init__.py
ac_core/auth.py
ac_core/constant.py
ac_core/language.py
ac_core/problem.py
ac_core/py.typed
ac_core/result.py
ac_core/submit.py
ac_core/url.py
ac_core/contest/__init__.py
ac_core/contest/listpage.py
ac_core/contest/standing.py
ac_core/contest/tasks.py
ac_core/interfaces/HttpUtil.py
ac_core/interfaces/__init__.py
ac_core/modal/__init__.py
ac_core/modal/problem_test_case.py
ac_core/utils/__init__.py
ac_core/utils/html_parse_helper.py
yxr_atcoder_core-0.0.3.5.dist-info/METADATA
yxr_atcoder_core-0.0.3.5.dist-info/WHEEL
yxr_atcoder_core-0.0.3.5.dist-info/licenses/LICENSE
yxr_atcoder_core-0.0.3.5.dist-info/RECORD
