Metadata-Version: 2.3
Name: yxr-atcoder-core
Version: 0.0.3.5
Summary: Simple Atcoder core api
Project-URL: Homepage, https://github.com/CroMarmot/yxr-atcoder-core
Project-URL: Bug Tracker, https://github.com/CroMarmot/yxr-atcoder-core/issues
Author-email: YeXiaoRain <yexiaorain@gmail.com>
License: MIT License
License-File: LICENSE
Keywords: api,atcoder,yxr
Classifier: License :: OSI Approved :: MIT License
Classifier: Programming Language :: Python :: 3
Requires-Python: >=3.8
Requires-Dist: beautifulsoup4>=4
Requires-Dist: dataclasses-json
Requires-Dist: lxml>=4
Requires-Dist: requests>=2
Requires-Dist: toml
Requires-Dist: types-beautifulsoup4
Provides-Extra: dev
Requires-Dist: build; extra == 'dev'
Requires-Dist: coverage>=6; extra == 'dev'
Requires-Dist: furo; extra == 'dev'
Requires-Dist: mypy; extra == 'dev'
Requires-Dist: myst-parser; extra == 'dev'
Requires-Dist: pytest>=7; extra == 'dev'
Requires-Dist: sphinx>=5; extra == 'dev'
Requires-Dist: yapf>=0.32; extra == 'dev'
Provides-Extra: doc
Requires-Dist: furo; extra == 'doc'
Requires-Dist: myst-parser; extra == 'doc'
Requires-Dist: sphinx>=5; extra == 'doc'
Provides-Extra: test
Requires-Dist: coverage>=6; extra == 'test'
Requires-Dist: mypy; extra == 'test'
Requires-Dist: pytest>=7; extra == 'test'
